biochain/__init__.py
biochain/__main__.py
biochain/base.py
biochain/cli.py
biochain-0.1.0.dist-info/LICENSE
biochain-0.1.0.dist-info/METADATA
biochain-0.1.0.dist-info/WHEEL
biochain-0.1.0.dist-info/entry_points.txt
biochain-0.1.0.dist-info/top_level.txt
biochain-0.1.0.dist-info/RECORD
